trytond/modules/health_services_imaging/COPYING
trytond/modules/health_services_imaging/README.rst
trytond/modules/health_services_imaging/__init__.py
trytond/modules/health_services_imaging/data/messages/messages.xml
trytond/modules/health_services_imaging/exceptions.py
trytond/modules/health_services_imaging/health_services_imaging.py
trytond/modules/health_services_imaging/health_services_imaging_view.xml
trytond/modules/health_services_imaging/locale/ar.po
trytond/modules/health_services_imaging/locale/de.po
trytond/modules/health_services_imaging/locale/el.po
trytond/modules/health_services_imaging/locale/eo.po
trytond/modules/health_services_imaging/locale/es.po
trytond/modules/health_services_imaging/locale/fr.po
trytond/modules/health_services_imaging/locale/health_services_imaging.pot
trytond/modules/health_services_imaging/locale/it_IT.po
trytond/modules/health_services_imaging/locale/ja_JP.po
trytond/modules/health_services_imaging/locale/ka.po
trytond/modules/health_services_imaging/locale/lo.po
trytond/modules/health_services_imaging/locale/pt_BR.po
trytond/modules/health_services_imaging/locale/sv.po
trytond/modules/health_services_imaging/locale/tr.po
trytond/modules/health_services_imaging/locale/uk.po
trytond/modules/health_services_imaging/locale/zh_CN.po
trytond/modules/health_services_imaging/pyproject.toml
trytond/modules/health_services_imaging/security/access_rights.xml
trytond/modules/health_services_imaging/tests/__init__.py
trytond/modules/health_services_imaging/tests/test_health_services_imaging.py
trytond/modules/health_services_imaging/tryton.cfg
trytond/modules/health_services_imaging/view/gnuhealth_imaging_request.xml
trytond/modules/health_services_imaging/view/gnuhealth_imaging_start_request.xml
trytond/modules/health_services_imaging/wizard/__init__.py
trytond/modules/health_services_imaging/wizard/create_health_service_invoice.xml
trytond/modules/health_services_imaging/wizard/wizard_health_services.py
gnuhealth_services_imaging-5.0.2.dist-info/METADATA
gnuhealth_services_imaging-5.0.2.dist-info/WHEEL
gnuhealth_services_imaging-5.0.2.dist-info/licenses/COPYING
gnuhealth_services_imaging-5.0.2.dist-info/RECORD
